Metadata-Version: 2.1
Name: odoo9-addon-purchase-request
Version: 9.0.1.0.3
Summary: Use this module to have notification of requirements of materials and/or external services and keep track of such requirements.
Home-page: UNKNOWN
Author: Eficent Business and IT Consulting Services S.L., Odoo Community Association (OCA)
Author-email: support@odoo-community.org
License: LGPL-3
Platform: UNKNOWN
Classifier: Programming Language :: Python
Classifier: Framework :: Odoo
Classifier: License :: OSI Approved :: GNU Lesser General Public License v3 (LGPLv3)
Requires-Python: ~=2.7
Requires-Dist: odoo (<9.1a,>=9.0a)
